LICENSE
README.md
setup.cfg
setup.py
calczx/__init__.py
calczx/main.py
calczx.egg-info/PKG-INFO
calczx.egg-info/SOURCES.txt
calczx.egg-info/dependency_links.txt
calczx.egg-info/requires.txt
calczx.egg-info/top_level.txt