Metadata-Version: 2.1
Name: calczx
Version: 1.3
Summary: TYPE YOUR DESCRIPTION HERE
Home-page: https://github.com/naistrai/calczx
Download-URL: https://github.com/naistrai/calczx/archive/v_01.tar.gz
Author: Nicetry
Author-email: admin@rizuki.my.id
License: MIT
Project-URL: Documentation, https://packaging.python.org/tutorials/distributing-packages/
Project-URL: Funding, https://github.com/naistrai/calczx
Project-URL: Say Thanks!, https://github.com/naistrai/calczx
Project-URL: Source, https://github.com/naistrai/calczx
Project-URL: Tracker, https://github.com/naistrai/calczx/issues
Keywords: SOME,MEANINGFULL,KEYWORDS
Classifier: Development Status :: 3 - Alpha
Classifier: Intended Audience :: Developers
Classifier: Topic :: Software Development :: Build Tools
Classifier: License :: OSI Approved :: MIT License
Classifier: Programming Language :: Python :: 3
Classifier: Programming Language :: Python :: 3.4
Classifier: Programming Language :: Python :: 3.5
Classifier: Programming Language :: Python :: 3.6
License-File: LICENSE
Requires-Dist: validators
Requires-Dist: beautifulsoup4
Requires-Dist: discordautochatdiscorudo
